{"generated_at":"2026-06-29T04:47:17Z","source":{"market_items":"https://api.warframe.market/v2/items","market_stats":"v1/items/{slug}/statistics"},"kind":"set_prices_only","test_limit":0,"count":231,"items":{"acceltra_prime_set":{"en_name":"Acceltra Prime Set","zh_name":null,"wa_price":39.407,"vaulted":null,"tags":["prime","primary","weapon","set"]},"aeolak_set":{"en_name":"Aeolak Set","zh_name":null,"wa_price":72.917,"vaulted":null,"tags":["primary","weapon","set"]},"afentis_prime_set":{"en_name":"Afentis Prime Set","zh_name":null,"wa_price":86.35,"vaulted":null,"tags":["prime","weapon","primary","set"]},"afuris_prime_set":{"en_name":"Afuris Prime Set","zh_name":null,"wa_price":110.567,"vaulted":null,"tags":["prime","secondary","weapon","set"]},"agkuza_set":{"en_name":"Agkuza Set","zh_name":null,"wa_price":50.714,"vaulted":null,"tags":["weapon","set","melee","archwing"]},"akarius_prime_set":{"en_name":"Akarius Prime Set","zh_name":null,"wa_price":69.385,"vaulted":null,"tags":["prime","secondary","weapon","set"]},"akbolto_prime_set":{"en_name":"Akbolto Prime Set","zh_name":null,"wa_price":98.733,"vaulted":null,"tags":["weapon","prime","secondary","set"]},"aklex_prime_set":{"en_name":"Aklex Prime Set","zh_name":null,"wa_price":37.894,"vaulted":null,"tags":["weapon","prime","set","secondary"]},"akjagara_prime_set":{"en_name":"Akjagara Prime Set","zh_name":null,"wa_price":98.6,"vaulted":null,"tags":["secondary","weapon","prime","set"]},"aksomati_prime_set":{"en_name":"Aksomati Prime Set","zh_name":null,"wa_price":99.3,"vaulted":null,"tags":["weapon","prime","secondary","set"]},"akstiletto_prime_set":{"en_name":"Akstiletto Prime Set","zh_name":null,"wa_price":99.294,"vaulted":null,"tags":["weapon","prime","secondary","set"]},"akvasto_prime_set":{"en_name":"Akvasto Prime Set","zh_name":null,"wa_price":59.852,"vaulted":null,"tags":["weapon","prime","set","secondary"]},"alternox_prime_set":{"en_name":"Alternox Prime Set","zh_name":null,"wa_price":29.016,"vaulted":null,"tags":["primary","prime","weapon","set"]},"akbronco_prime_set":{"en_name":"Akbronco Prime Set","zh_name":null,"wa_price":8.8,"vaulted":null,"tags":["weapon","prime","set","secondary"]},"amesha_set":{"en_name":"Amesha Set","zh_name":null,"wa_price":44.0,"vaulted":null,"tags":["set","archwing"]},"akmagnus_prime_set":{"en_name":"Akmagnus Prime Set","zh_name":null,"wa_price":34.767,"vaulted":null,"tags":["prime","secondary","weapon","set"]},"ambassador_set":{"en_name":"Ambassador Set","zh_name":null,"wa_price":29.059,"vaulted":null,"tags":["primary","weapon","set"]},"arum_spinosa_set":{"en_name":"Arum Spinosa Set","zh_name":null,"wa_price":24.0,"vaulted":null,"tags":["melee","weapon","set"]},"ankyros_prime_set":{"en_name":"Ankyros Prime Set","zh_name":null,"wa_price":44.136,"vaulted":null,"tags":["weapon","prime","set","melee"]},"athodai_prime_set":{"en_name":"Athodai Prime Set","zh_name":null,"wa_price":60.677,"vaulted":null,"tags":["prime","secondary","weapon","set"]},"athodai_set":{"en_name":"Athodai Set","zh_name":null,"wa_price":70.8,"vaulted":null,"tags":["weapon","secondary","set"]},"atlas_prime_set":{"en_name":"Atlas Prime Set","zh_name":null,"wa_price":64.982,"vaulted":null,"tags":["set","prime","warframe"]},"ballistica_prime_set":{"en_name":"Ballistica Prime Set","zh_name":null,"wa_price":145.69,"vaulted":null,"tags":["weapon","prime","secondary","set"]},"ash_prime_set":{"en_name":"Ash Prime Set","zh_name":null,"wa_price":69.33,"vaulted":null,"tags":["set","prime","warframe"]},"banshee_prime_set":{"en_name":"Banshee Prime Set","zh_name":null,"wa_price":79.87,"vaulted":null,"tags":["warframe","prime","set"]},"astilla_prime_set":{"en_name":"Astilla Prime Set","zh_name":null,"wa_price":49.667,"vaulted":null,"tags":["weapon","prime","set","primary"]},"baruuk_prime_set":{"en_name":"Baruuk Prime Set","zh_name":null,"wa_price":66.293,"vaulted":null,"tags":["prime","warframe","set"]},"bo_prime_set":{"en_name":"Bo Prime Set","zh_name":null,"wa_price":73.895,"vaulted":null,"tags":["weapon","prime","set","melee"]},"baza_prime_set":{"en_name":"Baza Prime Set","zh_name":null,"wa_price":79.533,"vaulted":null,"tags":["primary","prime","weapon","set"]},"bonewidow_set":{"en_name":"Bonewidow Set","zh_name":null,"wa_price":85.714,"vaulted":null,"tags":["necramech","set"]},"braton_prime_set":{"en_name":"Braton Prime Set","zh_name":null,"wa_price":8.536,"vaulted":null,"tags":["weapon","prime","set","primary"]},"braton_vandal_set":{"en_name":"Braton Vandal Set","zh_name":null,"wa_price":22.71,"vaulted":null,"tags":["primary","weapon","set"]},"boar_prime_set":{"en_name":"Boar Prime Set","zh_name":null,"wa_price":77.385,"vaulted":null,"tags":["weapon","prime","set","primary"]},"broken_war_set":{"en_name":"Broken War Set","zh_name":null,"wa_price":4.556,"vaulted":null,"tags":["melee","weapon","set"]},"bronco_prime_set":{"en_name":"Bronco Prime Set","zh_name":null,"wa_price":8.833,"vaulted":null,"tags":["weapon","prime","set","secondary"]},"burston_prime_set":{"en_name":"Burston Prime Set","zh_name":null,"wa_price":9.019,"vaulted":null,"tags":["weapon","prime","set","primary"]},"boltor_prime_set":{"en_name":"Boltor Prime Set","zh_name":null,"wa_price":38.931,"vaulted":null,"tags":["weapon","prime","set","primary"]},"caliban_prime_set":{"en_name":"Caliban Prime Set","zh_name":null,"wa_price":34.319,"vaulted":null,"tags":["warframe","prime","set"]},"carrier_prime_set":{"en_name":"Carrier Prime Set","zh_name":null,"wa_price":93.216,"vaulted":null,"tags":["sentinel","prime","set"]},"cedo_set":{"en_name":"Cedo Set","zh_name":null,"wa_price":19.25,"vaulted":null,"tags":["primary","weapon","set"]},"centaur_set":{"en_name":"Centaur Set","zh_name":null,"wa_price":65.0,"vaulted":null,"tags":["weapon","set","melee","archwing"]},"cernos_prime_set":{"en_name":"Cernos Prime Set","zh_name":null,"wa_price":59.556,"vaulted":null,"tags":["primary","prime","weapon","set"]},"carmine_penta_set":{"en_name":"Carmine Penta Set","zh_name":null,"wa_price":98.118,"vaulted":null,"tags":["weapon","primary","set"]},"chroma_prime_set":{"en_name":"Chroma Prime Set","zh_name":null,"wa_price":87.832,"vaulted":null,"tags":["set","prime","warframe"]},"cobra_and_crane_prime_set":{"en_name":"Cobra & Crane Prime Set","zh_name":null,"wa_price":26.25,"vaulted":null,"tags":["prime","weapon","melee","set"]},"cedo_prime_set":{"en_name":"Cedo Prime Set","zh_name":null,"wa_price":19.522,"vaulted":null,"tags":["primary","weapon","prime","set"]},"cinta_set":{"en_name":"Cinta Set","zh_name":null,"wa_price":80.0,"vaulted":null,"tags":["weapon","primary","set"]},"cortege_set":{"en_name":"Cortege Set","zh_name":null,"wa_price":107.0,"vaulted":null,"tags":["primary","archwing","weapon","set"]},"corinth_prime_set":{"en_name":"Corinth Prime Set","zh_name":null,"wa_price":81.485,"vaulted":null,"tags":["weapon","prime","set","primary"]},"corvas_prime_set":{"en_name":"Corvas Prime Set","zh_name":null,"wa_price":47.474,"vaulted":null,"tags":["archwing","primary","weapon","prime","set"]},"cyngas_set":{"en_name":"Cyngas Set","zh_name":null,"wa_price":65.0,"vaulted":null,"tags":["weapon","set","primary","archwing"]},"daikyu_prime_set":{"en_name":"Daikyu Prime Set","zh_name":null,"wa_price":19.53,"vaulted":null,"tags":["weapon","primary","prime","set"]},"dakra_prime_set":{"en_name":"Dakra Prime Set","zh_name":null,"wa_price":31.708,"vaulted":null,"tags":["weapon","prime","set","melee"]},"corufell_set":{"en_name":"Corufell Set","zh_name":null,"wa_price":35.75,"vaulted":null,"tags":["weapon","melee","set"]},"damaged_necramech_weapon_set":{"en_name":"Damaged Necramech Weapon Set","zh_name":null,"wa_price":15.0,"vaulted":null,"tags":["necramech","weapon","set"]},"corvas_set":{"en_name":"Corvas Set","zh_name":null,"wa_price":39.625,"vaulted":null,"tags":["weapon","set","primary","archwing"]},"damaged_necramech_set":{"en_name":"Damaged Necramech Set","zh_name":null,"wa_price":10.0,"vaulted":null,"tags":["necramech","set","mech"]},"dera_vandal_set":{"en_name":"Dera Vandal Set","zh_name":null,"wa_price":51.0,"vaulted":null,"tags":["primary","weapon","set"]},"dethcube_prime_set":{"en_name":"Dethcube Prime Set","zh_name":null,"wa_price":72.551,"vaulted":null,"tags":["set","prime","sentinel"]},"dual_decurion_set":{"en_name":"Dual Decurion Set","zh_name":null,"wa_price":40.625,"vaulted":null,"tags":["weapon","set","primary","archwing"]},"dual_keres_prime_set":{"en_name":"Dual Keres Prime Set","zh_name":null,"wa_price":60.714,"vaulted":null,"tags":["prime","melee","weapon","set"]},"dual_viciss_set":{"en_name":"Dual Viciss Set","zh_name":null,"wa_price":25.0,"vaulted":null,"tags":["weapon","melee","set"]},"dual_zoren_prime_set":{"en_name":"Dual Zoren Prime Set","zh_name":null,"wa_price":29.82,"vaulted":null,"tags":["melee","weapon","prime","set"]},"destreza_prime_set":{"en_name":"Destreza Prime Set","zh_name":null,"wa_price":125.472,"vaulted":null,"tags":["weapon","prime","set","melee"]},"efv_8_mars_set":{"en_name":"EFV-8 Mars Set","zh_name":null,"wa_price":20.0,"vaulted":null,"tags":["weapon","secondary","set"]},"efv_5_jupiter_set":{"en_name":"EFV-5 Jupiter Set","zh_name":null,"wa_price":20.0,"vaulted":null,"tags":["weapon","primary","set"]},"dual_kamas_prime_set":{"en_name":"Dual Kamas Prime Set","zh_name":null,"wa_price":76.846,"vaulted":null,"tags":["weapon","prime","set","melee"]},"epitaph_prime_set":{"en_name":"Epitaph Prime Set","zh_name":null,"wa_price":14.7,"vaulted":null,"tags":["prime","secondary","weapon","set"]},"elytron_set":{"en_name":"Elytron Set","zh_name":null,"wa_price":30.0,"vaulted":null,"tags":["set","archwing"]},"equinox_prime_set":{"en_name":"Equinox Prime Set","zh_name":null,"wa_price":60.888,"vaulted":null,"tags":["set","prime","warframe"]},"euphona_prime_set":{"en_name":"Euphona Prime Set","zh_name":null,"wa_price":58.222,"vaulted":null,"tags":["prime","weapon","secondary","set"]},"fang_prime_set":{"en_name":"Fang Prime Set","zh_name":null,"wa_price":8.87,"vaulted":null,"tags":["weapon","prime","set","melee"]},"ember_prime_set":{"en_name":"Ember Prime Set","zh_name":null,"wa_price":64.279,"vaulted":null,"tags":["set","prime","warframe"]},"fluctus_set":{"en_name":"Fluctus Set","zh_name":null,"wa_price":45.0,"vaulted":null,"tags":["weapon","set","primary","archwing"]},"epitaph_set":{"en_name":"Epitaph Set","zh_name":null,"wa_price":8.1,"vaulted":null,"tags":["weapon","secondary","set"]},"frost_prime_set":{"en_name":"Frost Prime Set","zh_name":null,"wa_price":78.17,"vaulted":null,"tags":["set","prime","warframe"]},"fragor_prime_set":{"en_name":"Fragor Prime Set","zh_name":null,"wa_price":38.471,"vaulted":null,"tags":["weapon","prime","set","melee"]},"fulmin_prime_set":{"en_name":"Fulmin Prime Set","zh_name":null,"wa_price":38.687,"vaulted":null,"tags":["primary","prime","weapon","set"]},"galatine_prime_set":{"en_name":"Galatine Prime Set","zh_name":null,"wa_price":55.538,"vaulted":null,"tags":["weapon","prime","set","melee"]},"garuda_prime_set":{"en_name":"Garuda Prime Set","zh_name":null,"wa_price":89.496,"vaulted":null,"tags":["warframe","prime","set"]},"gauss_prime_set":{"en_name":"Gauss Prime Set","zh_name":null,"wa_price":49.532,"vaulted":null,"tags":["prime","warframe","set"]},"ghoulsaw_set":{"en_name":"Ghoulsaw Set","zh_name":null,"wa_price":10.0,"vaulted":null,"tags":["melee","weapon","set"]},"furax_wraith_set":{"en_name":"Furax Wraith Set","zh_name":null,"wa_price":13.944,"vaulted":null,"tags":["weapon","melee","set"]},"glaive_prime_set":{"en_name":"Glaive Prime Set","zh_name":null,"wa_price":69.571,"vaulted":null,"tags":["weapon","prime","set","melee"]},"gram_prime_set":{"en_name":"Gram Prime Set","zh_name":null,"wa_price":36.586,"vaulted":null,"tags":["weapon","prime","set","melee"]},"gara_prime_set":{"en_name":"Gara Prime Set","zh_name":null,"wa_price":71.495,"vaulted":null,"tags":["warframe","prime","set"]},"gorgon_wraith_set":{"en_name":"Gorgon Wraith Set","zh_name":null,"wa_price":10.391,"vaulted":null,"tags":["primary","weapon","set"]},"gunsen_prime_set":{"en_name":"Gunsen Prime Set","zh_name":null,"wa_price":54.641,"vaulted":null,"tags":["melee","prime","weapon","set"]},"grendel_prime_set":{"en_name":"Grendel Prime Set","zh_name":null,"wa_price":53.954,"vaulted":null,"tags":["prime","warframe","set"]},"harrow_prime_set":{"en_name":"Harrow Prime Set","zh_name":null,"wa_price":65.212,"vaulted":null,"tags":["warframe","prime","set"]},"helios_prime_set":{"en_name":"Helios Prime Set","zh_name":null,"wa_price":72.121,"vaulted":null,"tags":["prime","sentinel","set"]},"hespar_set":{"en_name":"Hespar Set","zh_name":null,"wa_price":145.667,"vaulted":null,"tags":["melee","weapon","set"]},"hikou_prime_set":{"en_name":"Hikou Prime Set","zh_name":null,"wa_price":38.5,"vaulted":null,"tags":["weapon","prime","set","secondary"]},"guandao_prime_set":{"en_name":"Guandao Prime Set","zh_name":null,"wa_price":56.905,"vaulted":null,"tags":["weapon","prime","set","melee"]},"gyre_prime_set":{"en_name":"Gyre Prime Set","zh_name":null,"wa_price":31.202,"vaulted":null,"tags":["warframe","prime","set"]},"hildryn_prime_set":{"en_name":"Hildryn Prime Set","zh_name":null,"wa_price":66.377,"vaulted":null,"tags":["warframe","prime","set"]},"hydroid_prime_set":{"en_name":"Hydroid Prime Set","zh_name":null,"wa_price":91.135,"vaulted":null,"tags":["warframe","prime","set"]},"hystrix_prime_set":{"en_name":"Hystrix Prime Set","zh_name":null,"wa_price":30.632,"vaulted":null,"tags":["secondary","prime","weapon","set"]},"imperator_vandal_set":{"en_name":"Imperator Vandal Set","zh_name":null,"wa_price":46.25,"vaulted":null,"tags":["weapon","set","primary","archwing"]},"itzal_set":{"en_name":"Itzal Set","zh_name":null,"wa_price":40.0,"vaulted":null,"tags":["set","archwing"]},"karak_wraith_set":{"en_name":"Karak Wraith Set","zh_name":null,"wa_price":66.182,"vaulted":null,"tags":["primary","weapon","set"]},"karyst_prime_set":{"en_name":"Karyst Prime Set","zh_name":null,"wa_price":32.69,"vaulted":null,"tags":["weapon","prime","set","melee"]},"kaszas_set":{"en_name":"Kaszas Set","zh_name":null,"wa_price":19.0,"vaulted":null,"tags":["weapon","set","melee","archwing"]},"inaros_prime_set":{"en_name":"Inaros Prime Set","zh_name":null,"wa_price":67.797,"vaulted":null,"tags":["set","prime","warframe"]},"ivara_prime_set":{"en_name":"Ivara Prime Set","zh_name":null,"wa_price":66.337,"vaulted":null,"tags":["set","prime","warframe"]},"kavasa_prime_kubrow_collar_set":{"en_name":"Kavasa Prime Kubrow Collar Set","zh_name":null,"wa_price":25.1,"vaulted":null,"tags":["prime","skin","set"]},"kestrel_prime_set":{"en_name":"Kestrel Prime Set","zh_name":null,"wa_price":27.342,"vaulted":null,"tags":["prime","weapon","melee","set"]},"knell_prime_set":{"en_name":"Knell Prime Set","zh_name":null,"wa_price":39.233,"vaulted":null,"tags":["secondary","weapon","prime","set"]},"kogake_prime_set":{"en_name":"Kogake Prime Set","zh_name":null,"wa_price":100.0,"vaulted":null,"tags":["weapon","prime","set","melee"]},"kronen_prime_set":{"en_name":"Kronen Prime Set","zh_name":null,"wa_price":103.529,"vaulted":null,"tags":["weapon","prime","set","melee"]},"kompressa_prime_set":{"en_name":"Kompressa Prime Set","zh_name":null,"wa_price":14.072,"vaulted":null,"tags":["secondary","weapon","prime","set"]},"lato_vandal_set":{"en_name":"Lato Vandal Set","zh_name":null,"wa_price":15.603,"vaulted":null,"tags":["weapon","secondary","set"]},"latron_prime_set":{"en_name":"Latron Prime Set","zh_name":null,"wa_price":70.0,"vaulted":null,"tags":["weapon","prime","set","primary"]},"latron_wraith_set":{"en_name":"Latron Wraith Set","zh_name":null,"wa_price":65.1,"vaulted":null,"tags":["primary","weapon","set"]},"khora_prime_set":{"en_name":"Khora Prime Set","zh_name":null,"wa_price":79.954,"vaulted":null,"tags":["prime","warframe","set"]},"lex_prime_set":{"en_name":"Lex Prime Set","zh_name":null,"wa_price":7.979,"vaulted":null,"tags":["weapon","prime","set","secondary"]},"lavos_prime_set":{"en_name":"Lavos Prime Set","zh_name":null,"wa_price":20.781,"vaulted":null,"tags":["warframe","prime","set"]},"limbo_prime_set":{"en_name":"Limbo Prime Set","zh_name":null,"wa_price":95.468,"vaulted":null,"tags":["set","prime","warframe"]},"larkspur_prime_set":{"en_name":"Larkspur Prime Set","zh_name":null,"wa_price":60.183,"vaulted":null,"tags":["prime","archwing","weapon","primary","set"]},"mag_prime_set":{"en_name":"Mag Prime Set","zh_name":null,"wa_price":73.0,"vaulted":null,"tags":["set","prime","warframe"]},"magnus_prime_set":{"en_name":"Magnus Prime Set","zh_name":null,"wa_price":43.538,"vaulted":null,"tags":["secondary","weapon","prime","set"]},"mandonel_set":{"en_name":"Mandonel Set","zh_name":null,"wa_price":11.348,"vaulted":null,"tags":["archwing","primary","weapon","set"]},"masseter_prime_set":{"en_name":"Masseter Prime Set","zh_name":null,"wa_price":14.966,"vaulted":null,"tags":["prime","melee","weapon","set"]},"mantis_set":{"en_name":"Mantis Set","zh_name":null,"wa_price":20.333,"vaulted":null,"tags":["set"]},"loki_prime_set":{"en_name":"Loki Prime Set","zh_name":null,"wa_price":76.488,"vaulted":null,"tags":["set","prime","warframe"]},"mirage_prime_set":{"en_name":"Mirage Prime Set","zh_name":null,"wa_price":85.384,"vaulted":null,"tags":["warframe","prime","set"]},"nagantaka_prime_set":{"en_name":"Nagantaka Prime Set","zh_name":null,"wa_price":40.857,"vaulted":null,"tags":["primary","weapon","prime","set"]},"nami_skyla_prime_set":{"en_name":"Nami Skyla Prime Set","zh_name":null,"wa_price":99.778,"vaulted":null,"tags":["weapon","prime","set","melee"]},"nautilus_prime_set":{"en_name":"Nautilus Prime Set","zh_name":null,"wa_price":35.425,"vaulted":null,"tags":["prime","sentinel","set"]},"nautilus_set":{"en_name":"Nautilus Set","zh_name":null,"wa_price":66.25,"vaulted":null,"tags":["sentinel","set"]},"mesa_prime_set":{"en_name":"Mesa Prime Set","zh_name":null,"wa_price":57.024,"vaulted":null,"tags":["set","prime","warframe"]},"morgha_set":{"en_name":"Morgha Set","zh_name":null,"wa_price":127.5,"vaulted":null,"tags":["primary","archwing","weapon","set"]},"nekros_prime_set":{"en_name":"Nekros Prime Set","zh_name":null,"wa_price":89.936,"vaulted":null,"tags":["set","warframe","prime"]},"nezha_prime_set":{"en_name":"Nezha Prime Set","zh_name":null,"wa_price":71.609,"vaulted":null,"tags":["set","prime","warframe"]},"ninkondi_prime_set":{"en_name":"Ninkondi Prime Set","zh_name":null,"wa_price":61.775,"vaulted":null,"tags":["weapon","prime","set","melee"]},"nikana_prime_set":{"en_name":"Nikana Prime Set","zh_name":null,"wa_price":69.111,"vaulted":null,"tags":["weapon","prime","set","melee"]},"nova_prime_set":{"en_name":"Nova Prime Set","zh_name":null,"wa_price":68.97,"vaulted":null,"tags":["set","prime","warframe"]},"oberon_prime_set":{"en_name":"Oberon Prime Set","zh_name":null,"wa_price":81.556,"vaulted":null,"tags":["warframe","prime","set"]},"nyx_prime_set":{"en_name":"Nyx Prime Set","zh_name":null,"wa_price":51.832,"vaulted":null,"tags":["set","prime","warframe"]},"odonata_prime_set":{"en_name":"Odonata Prime Set","zh_name":null,"wa_price":39.1,"vaulted":null,"tags":["prime","set","archwing"]},"octavia_prime_set":{"en_name":"Octavia Prime Set","zh_name":null,"wa_price":83.13,"vaulted":null,"tags":["warframe","prime","set"]},"okina_prime_set":{"en_name":"Okina Prime Set","zh_name":null,"wa_price":49.637,"vaulted":null,"tags":["weapon","melee","prime","set"]},"orthos_prime_set":{"en_name":"Orthos Prime Set","zh_name":null,"wa_price":10.738,"vaulted":null,"tags":["weapon","prime","set","melee"]},"pandero_prime_set":{"en_name":"Pandero Prime Set","zh_name":null,"wa_price":33.667,"vaulted":null,"tags":["weapon","prime","set","secondary"]},"pangolin_prime_set":{"en_name":"Pangolin Prime Set","zh_name":null,"wa_price":37.429,"vaulted":null,"tags":["weapon","prime","set","melee"]},"onorix_set":{"en_name":"Onorix Set","zh_name":null,"wa_price":32.429,"vaulted":null,"tags":["weapon","set","melee","archwing"]},"panthera_prime_set":{"en_name":"Panthera Prime Set","zh_name":null,"wa_price":69.593,"vaulted":null,"tags":["weapon","prime","set","primary"]},"parallax_set":{"en_name":"Parallax Set","zh_name":null,"wa_price":15.168,"vaulted":null,"tags":["set"]},"paris_prime_set":{"en_name":"Paris Prime Set","zh_name":null,"wa_price":9.643,"vaulted":null,"tags":["weapon","prime","set","primary"]},"pathocyst_set":{"en_name":"Pathocyst Set","zh_name":null,"wa_price":35.833,"vaulted":null,"tags":["weapon","melee","set"]},"perigale_prime_set":{"en_name":"Perigale Prime Set","zh_name":null,"wa_price":31.281,"vaulted":null,"tags":["weapon","primary","prime","set"]},"phaedra_set":{"en_name":"Phaedra Set","zh_name":null,"wa_price":45.0,"vaulted":null,"tags":["weapon","set","primary","archwing"]},"perigale_set":{"en_name":"Perigale Set","zh_name":null,"wa_price":4.923,"vaulted":null,"tags":["primary","weapon","set"]},"nidus_prime_set":{"en_name":"Nidus Prime Set","zh_name":null,"wa_price":91.539,"vaulted":null,"tags":["warframe","prime","set"]},"prisma_shade":{"en_name":"Prisma Shade","zh_name":null,"wa_price":46.0,"vaulted":null,"tags":["sentinel","set"]},"phantasma_prime_set":{"en_name":"Phantasma Prime Set","zh_name":null,"wa_price":70.186,"vaulted":null,"tags":["weapon","prime","primary","set"]},"purgator_1_set":{"en_name":"Purgator 1 Set","zh_name":null,"wa_price":25.0,"vaulted":null,"tags":["weapon","primary","set"]},"pyrana_prime_set":{"en_name":"Pyrana Prime Set","zh_name":null,"wa_price":60.68,"vaulted":null,"tags":["weapon","prime","secondary","set"]},"quassus_prime_set":{"en_name":"Quassus Prime Set","zh_name":null,"wa_price":27.419,"vaulted":null,"tags":["melee","weapon","prime","set"]},"rathbone_set":{"en_name":"Rathbone Set","zh_name":null,"wa_price":44.5,"vaulted":null,"tags":["weapon","set","melee","archwing"]},"prisma_shade_set":{"en_name":"Prisma Shade Set","zh_name":null,"wa_price":69.5,"vaulted":null,"tags":["sentinel","set"]},"rauta_set":{"en_name":"Rauta Set","zh_name":null,"wa_price":58.333,"vaulted":null,"tags":["weapon","primary","set"]},"protea_prime_set":{"en_name":"Protea Prime Set","zh_name":null,"wa_price":33.269,"vaulted":null,"tags":["warframe","prime","set"]},"reconifex_set":{"en_name":"Reconifex Set","zh_name":null,"wa_price":15.0,"vaulted":null,"tags":["weapon","primary","set"]},"redeemer_prime_set":{"en_name":"Redeemer Prime Set","zh_name":null,"wa_price":49.047,"vaulted":null,"tags":["weapon","prime","set","melee"]},"reaper_prime_set":{"en_name":"Reaper Prime Set","zh_name":null,"wa_price":29.75,"vaulted":null,"tags":["prime","weapon","melee","set"]},"revenant_prime_set":{"en_name":"Revenant Prime Set","zh_name":null,"wa_price":63.601,"vaulted":null,"tags":["prime","warframe","set"]},"riot_848_set":{"en_name":"Riot-848 Set","zh_name":null,"wa_price":25.0,"vaulted":null,"tags":["weapon","secondary","set"]},"rhino_prime_set":{"en_name":"Rhino Prime Set","zh_name":null,"wa_price":54.137,"vaulted":null,"tags":["set","prime","warframe"]},"sarofang_set":{"en_name":"Sarofang Set","zh_name":null,"wa_price":4.0,"vaulted":null,"tags":["melee","weapon","set"]},"sarofang_prime_set":{"en_name":"Sarofang Prime Set","zh_name":null,"wa_price":29.505,"vaulted":null,"tags":["melee","weapon","prime","set"]},"scimitar_set":{"en_name":"Scimitar Set","zh_name":null,"wa_price":19.375,"vaulted":null,"tags":["set"]},"scindo_prime_set":{"en_name":"Scindo Prime Set","zh_name":null,"wa_price":20.972,"vaulted":null,"tags":["weapon","prime","set","melee"]},"rubico_prime_set":{"en_name":"Rubico Prime Set","zh_name":null,"wa_price":45.974,"vaulted":null,"tags":["weapon","prime","set","primary"]},"scourge_prime_set":{"en_name":"Scourge Prime Set","zh_name":null,"wa_price":82.361,"vaulted":null,"tags":["primary","weapon","prime","set"]},"shade_prime_set":{"en_name":"Shade Prime Set","zh_name":null,"wa_price":48.475,"vaulted":null,"tags":["prime","sentinel","set"]},"sevagoth_prime_set":{"en_name":"Sevagoth Prime Set","zh_name":null,"wa_price":29.305,"vaulted":null,"tags":["prime","warframe","set"]},"sheev_set":{"en_name":"Sheev Set","zh_name":null,"wa_price":29.667,"vaulted":null,"tags":["melee","weapon","set"]},"shedu_set":{"en_name":"Shedu Set","zh_name":null,"wa_price":47.182,"vaulted":null,"tags":["primary","weapon","set"]},"sicarus_prime_set":{"en_name":"Sicarus Prime Set","zh_name":null,"wa_price":58.609,"vaulted":null,"tags":["weapon","prime","set","secondary"]},"silva_and_aegis_prime_set":{"en_name":"Silva & Aegis Prime Set","zh_name":null,"wa_price":55.278,"vaulted":null,"tags":["weapon","prime","melee","set"]},"soma_prime_set":{"en_name":"Soma Prime Set","zh_name":null,"wa_price":54.063,"vaulted":null,"tags":["weapon","prime","set","primary"]},"spectra_vandal_set":{"en_name":"Spectra Vandal Set","zh_name":null,"wa_price":17.667,"vaulted":null,"tags":["weapon","modular","secondary","set"]},"spira_prime_set":{"en_name":"Spira Prime Set","zh_name":null,"wa_price":99.571,"vaulted":null,"tags":["weapon","prime","set","secondary"]},"sporothrix_set":{"en_name":"Sporothrix Set","zh_name":null,"wa_price":22.222,"vaulted":null,"tags":["primary","weapon","set"]},"stahlta_set":{"en_name":"Stahlta Set","zh_name":null,"wa_price":29.048,"vaulted":null,"tags":["primary","weapon","set"]},"snipetron_vandal_set":{"en_name":"Snipetron Vandal Set","zh_name":null,"wa_price":47.0,"vaulted":null,"tags":["weapon","primary","set"]},"steflos_set":{"en_name":"Steflos Set","zh_name":null,"wa_price":31.667,"vaulted":null,"tags":["weapon","primary","set"]},"saryn_prime_set":{"en_name":"Saryn Prime Set","zh_name":null,"wa_price":76.811,"vaulted":null,"tags":["set","prime","warframe"]},"stradavar_prime_set":{"en_name":"Stradavar Prime Set","zh_name":null,"wa_price":35.093,"vaulted":null,"tags":["weapon","prime","set","primary"]},"stropha_set":{"en_name":"Stropha Set","zh_name":null,"wa_price":25.6,"vaulted":null,"tags":["weapon","melee","set"]},"strun_wraith_set":{"en_name":"Strun Wraith Set","zh_name":null,"wa_price":63.421,"vaulted":null,"tags":["weapon","primary","set"]},"strun_prime_set":{"en_name":"Strun Prime Set","zh_name":null,"wa_price":51.774,"vaulted":null,"tags":["primary","weapon","prime","set"]},"tatsu_prime_set":{"en_name":"Tatsu Prime Set","zh_name":null,"wa_price":32.0,"vaulted":null,"tags":["weapon","prime","melee","set"]},"tekko_prime_set":{"en_name":"Tekko Prime Set","zh_name":null,"wa_price":70.88,"vaulted":null,"tags":["weapon","prime","set","melee"]},"tenora_prime_set":{"en_name":"Tenora Prime Set","zh_name":null,"wa_price":68.947,"vaulted":null,"tags":["weapon","prime","set","primary"]},"tiberon_prime_set":{"en_name":"Tiberon Prime Set","zh_name":null,"wa_price":58.952,"vaulted":null,"tags":["weapon","prime","set","primary"]},"sybaris_prime_set":{"en_name":"Sybaris Prime Set","zh_name":null,"wa_price":76.853,"vaulted":null,"tags":["primary","prime","weapon","set"]},"styanax_prime_set":{"en_name":"Styanax Prime Set","zh_name":null,"wa_price":83.555,"vaulted":null,"tags":["warframe","prime","set"]},"tigris_prime_set":{"en_name":"Tigris Prime Set","zh_name":null,"wa_price":55.968,"vaulted":null,"tags":["primary","prime","weapon","set"]},"titania_prime_set":{"en_name":"Titania Prime Set","zh_name":null,"wa_price":74.304,"vaulted":null,"tags":["set","prime","warframe"]},"trinity_prime_set":{"en_name":"Trinity Prime Set","zh_name":null,"wa_price":49.226,"vaulted":null,"tags":["set","warframe","prime"]},"tipedo_prime_set":{"en_name":"Tipedo Prime Set","zh_name":null,"wa_price":63.393,"vaulted":null,"tags":["weapon","prime","set","melee"]},"vadarya_prime_set":{"en_name":"Vadarya Prime Set","zh_name":null,"wa_price":15.009,"vaulted":null,"tags":["weapon","primary","prime","set"]},"valkyr_prime_set":{"en_name":"Valkyr Prime Set","zh_name":null,"wa_price":72.523,"vaulted":null,"tags":["prime","warframe","set"]},"vasto_prime_set":{"en_name":"Vasto Prime Set","zh_name":null,"wa_price":26.317,"vaulted":null,"tags":["weapon","prime","set","secondary"]},"vauban_prime_set":{"en_name":"Vauban Prime Set","zh_name":null,"wa_price":109.177,"vaulted":null,"tags":["set","prime","warframe"]},"twin_vipers_wraith_set":{"en_name":"Twin Vipers Wraith Set","zh_name":null,"wa_price":70.25,"vaulted":null,"tags":["weapon","secondary","set"]},"vectis_prime_set":{"en_name":"Vectis Prime Set","zh_name":null,"wa_price":139.197,"vaulted":null,"tags":["weapon","prime","set","primary"]},"trumna_prime_set":{"en_name":"Trumna Prime Set","zh_name":null,"wa_price":24.078,"vaulted":null,"tags":["primary","weapon","prime","set"]},"velocitus_set":{"en_name":"Velocitus Set","zh_name":null,"wa_price":45.0,"vaulted":null,"tags":["weapon","set","primary","archwing"]},"velox_prime_set":{"en_name":"Velox Prime Set","zh_name":null,"wa_price":14.263,"vaulted":null,"tags":["weapon","secondary","prime","set"]},"velox_set":{"en_name":"Velox Set","zh_name":null,"wa_price":14.833,"vaulted":null,"tags":["weapon","secondary","set"]},"venato_prime_set":{"en_name":"Venato Prime Set","zh_name":null,"wa_price":14.41,"vaulted":null,"tags":["weapon","prime","melee","set"]},"voidrig_set":{"en_name":"Voidrig Set","zh_name":null,"wa_price":59.449,"vaulted":null,"tags":["necramech","set"]},"volnus_prime_set":{"en_name":"Volnus Prime Set","zh_name":null,"wa_price":38.0,"vaulted":null,"tags":["weapon","prime","set","melee"]},"volt_prime_set":{"en_name":"Volt Prime Set","zh_name":null,"wa_price":64.83,"vaulted":null,"tags":["set","prime","warframe"]},"venka_prime_set":{"en_name":"Venka Prime Set","zh_name":null,"wa_price":57.714,"vaulted":null,"tags":["weapon","prime","melee","set"]},"vesper_77_set":{"en_name":"Vesper 77 Set","zh_name":null,"wa_price":15.0,"vaulted":null,"tags":["weapon","secondary","set"]},"voruna_prime_set":{"en_name":"Voruna Prime Set","zh_name":null,"wa_price":49.716,"vaulted":null,"tags":["warframe","prime","set"]},"wisp_prime_set":{"en_name":"Wisp Prime Set","zh_name":null,"wa_price":69.382,"vaulted":null,"tags":["prime","warframe","set"]},"wolf_sledge_set":{"en_name":"Wolf Sledge Set","zh_name":null,"wa_price":44.133,"vaulted":null,"tags":["melee","weapon","set"]},"wukong_prime_set":{"en_name":"Wukong Prime Set","zh_name":null,"wa_price":66.968,"vaulted":null,"tags":["set","prime","warframe"]},"wyrm_prime_set":{"en_name":"Wyrm Prime Set","zh_name":null,"wa_price":72.652,"vaulted":null,"tags":["sentinel","prime","set"]},"yareli_prime_set":{"en_name":"Yareli Prime Set","zh_name":null,"wa_price":29.633,"vaulted":null,"tags":["warframe","prime","set"]},"zakti_prime_set":{"en_name":"Zakti Prime Set","zh_name":null,"wa_price":39.625,"vaulted":null,"tags":["weapon","prime","secondary","set"]},"zephyr_prime_set":{"en_name":"Zephyr Prime Set","zh_name":null,"wa_price":71.781,"vaulted":null,"tags":["prime","warframe","set"]},"xiphos_set":{"en_name":"Xiphos Set","zh_name":null,"wa_price":5200.0,"vaulted":null,"tags":["set"]},"xaku_prime_set":{"en_name":"Xaku Prime Set","zh_name":null,"wa_price":24.046,"vaulted":null,"tags":["warframe","prime","set"]},"zhuge_prime_set":{"en_name":"Zhuge Prime Set","zh_name":null,"wa_price":49.719,"vaulted":null,"tags":["primary","prime","weapon","set"]},"zylok_prime_set":{"en_name":"Zylok Prime Set","zh_name":null,"wa_price":21.064,"vaulted":null,"tags":["prime","secondary","weapon","set"]}}}